<?xml version="1.0"?>
<MethodSetup Method="Cuts::CutsSA">
  <GeneralInfo>
    <Info name="TMVA Release" value="4.2.0 [262656]"/>
    <Info name="ROOT Release" value="6.02/13 [393741]"/>
    <Info name="Creator" value="jwang"/>
    <Info name="Date" value="Tue Jun 13 12:37:35 2017"/>
    <Info name="Host" value="Linux vocms029.cern.ch 2.6.32-504.12.2.el6.x86_64 #1 SMP Thu Mar 12 07:33:00 CET 2015 x86_64 x86_64 x86_64 GNU/Linux"/>
    <Info name="Dir" value="/net/hisrv0001/home/jwang/tmvaDjet/CMSSW_7_5_8_patch3/src/tmvaDjet/myTMVA"/>
    <Info name="Training events" value="23251"/>
    <Info name="TrainingTime" value="3.79150600e+01"/>
    <Info name="AnalysisType" value="Classification"/>
  </GeneralInfo>
  <Options>
    <Option name="V" modified="Yes">False</Option>
    <Option name="VerbosityLevel" modified="No">Default</Option>
    <Option name="VarTransform" modified="No">None</Option>
    <Option name="H" modified="Yes">False</Option>
    <Option name="CreateMVAPdfs" modified="No">False</Option>
    <Option name="IgnoreNegWeightsInTraining" modified="No">False</Option>
    <Option name="FitMethod" modified="Yes">SA</Option>
    <Option name="EffMethod" modified="Yes">EffSel</Option>
    <Option name="CutRangeMin" size="2" modified="No">-1.000000e+00 -1.000000e+00</Option>
    <Option name="CutRangeMax" size="2" modified="No">-1.000000e+00 -1.000000e+00</Option>
    <Option name="VarProp" size="2" modified="No">FMin FMax</Option>
  </Options>
  <Variables NVar="2">
    <Variable VarIndex="0" Expression="Dalpha" Label="Dalpha" Title="Dalpha" Unit="" Internal="Dalpha" Type="F" Min="1.39020354e-04" Max="1.99958712e-01"/>
    <Variable VarIndex="1" Expression="(DsvpvDistance/DsvpvDisErr)" Label="(DsvpvDistance/DsvpvDisErr)" Title="(DsvpvDistance/DsvpvDisErr)" Unit="" Internal="_DsvpvDistance_D_DsvpvDisErr_" Type="F" Min="2.22697519e-02" Max="1.28686462e+03"/>
  </Variables>
  <Spectators NSpec="0"/>
  <Classes NClass="2">
    <Class Name="Signal" Index="0"/>
    <Class Name="Background" Index="1"/>
  </Classes>
  <Transformations NTransformations="0"/>
  <MVAPdfs/>
  <Weights OptimisationMethod="0" FitMethod="2" nbins="100">
    <!--Below are the optimised cuts for 2 variables: Format: ibin(hist) effS effB cutMin[ivar=0] cutMax[ivar=0] ... cutMin[ivar=n-1] cutMax[ivar=n-1]-->
    <Bin ibin="1" effS="0.0000000000000000e+00" effB="0.0000000000000000e+00">
      <Cuts cutMin_0="-1.0000000000000000e+30" cutMax_0="2.2649973360971938e-03" cutMin_1="8.8003139424371255e+01" cutMax_1="1.0000000000000000e+30"/>
    </Bin>
    <Bin ibin="2" effS="1.0000000000000000e-02" effB="1.2817226524930447e-04">
      <Cuts cutMin_0="-1.0000000000000000e+30" cutMax_0="2.2275767236068300e-03" cutMin_1="2.2570949237860965e+01" cutMax_1="1.0000000000000000e+30"/>
    </Bin>
    <Bin ibin="3" effS="2.0000000000000000e-02" effB="3.2043067039921880e-04">
      <Cuts cutMin_0="-1.0000000000000000e+30" cutMax_0="6.0423975956179063e-03" cutMin_1="2.7986216094288416e+01" cutMax_1="1.0000000000000000e+30"/>
    </Bin>
    <Bin ibin="4" effS="2.9999999999999999e-02" effB="3.8451678119599819e-04">
      <Cuts cutMin_0="-1.0000000000000000e+30" cutMax_0="5.1463897830154636e-03" cutMin_1="2.2191373609674244e+01" cutMax_1="1.0000000000000000e+30"/>
    </Bin>
    <Bin ibin="5" effS="4.0000000000000001e-02" effB="2.5634453049860895e-04">
      <Cuts cutMin_0="-1.0000000000000000e+30" cutMax_0="3.7448592076830987e-03" cutMin_1="1.4479736192842816e+01" cutMax_1="1.0000000000000000e+30"/>
    </Bin>
    <Bin ibin="6" effS="5.0000000000000003e-02" effB="5.7677517179399729e-04">
      <Cuts cutMin_0="-1.0000000000000000e+30" cutMax_0="7.5447176422958279e-03" cutMin_1="1.9569992215997559e+01" cutMax_1="1.0000000000000000e+30"/>
    </Bin>
    <Bin ibin="7" effS="5.9999999999999998e-02" effB="5.1268906099721789e-04">
      <Cuts cutMin_0="-1.0000000000000000e+30" cutMax_0="3.6374617810697929e-03" cutMin_1="1.0563021463865754e+01" cutMax_1="1.0000000000000000e+30"/>
    </Bin>
    <Bin ibin="8" effS="7.0000000000000007e-02" effB="7.6903356239199638e-04">
      <Cuts cutMin_0="-1.0000000000000000e+30" cutMax_0="4.6486937837897681e-03" cutMin_1="1.1377542027040125e+01" cutMax_1="1.0000000000000000e+30"/>
    </Bin>
    <Bin ibin="9" effS="8.0000000000000002e-02" effB="7.6903356239199638e-04">
      <Cuts cutMin_0="-1.0000000000000000e+30" cutMax_0="4.6509849280180369e-03" cutMin_1="1.0517219271895234e+01" cutMax_1="1.0000000000000000e+30"/>
    </Bin>
    <Bin ibin="10" effS="8.9999999999999997e-02" effB="1.7944116843864322e-03">
      <Cuts cutMin_0="-1.0000000000000000e+30" cutMax_0="1.5621169033145269e-02" cutMin_1="1.6852864781641177e+01" cutMax_1="1.0000000000000000e+30"/>
    </Bin>
    <Bin ibin="11" effS="1.0000000000000001e-01" effB="1.2176365125924349e-03">
      <Cuts cutMin_0="-1.0000000000000000e+30" cutMax_0="4.1102933991368296e-03" cutMin_1="2.2363101751012877e+00" cutMax_1="1.0000000000000000e+30"/>
    </Bin>
    <Bin ibin="12" effS="1.1000000000000000e-01" effB="1.8584978533908725e-03">
      <Cuts cutMin_0="-1.0000000000000000e+30" cutMax_0="4.3054883579454204e-03" cutMin_1="1.5961905191596395e+00" cutMax_1="1.0000000000000000e+30"/>
    </Bin>
    <Bin ibin="13" effS="1.2000000000000000e-01" effB="1.0894642909988761e-03">
      <Cuts cutMin_0="-1.0000000000000000e+30" cutMax_0="5.6807078258344053e-03" cutMin_1="7.7106405291361861e+00" cutMax_1="1.0000000000000000e+30"/>
    </Bin>
    <Bin ibin="14" effS="1.3000000000000000e-01" effB="2.1148424129933119e-03">
      <Cuts cutMin_0="-1.0000000000000000e+30" cutMax_0="1.3861770428046542e-02" cutMin_1="1.3279596351810030e+01" cutMax_1="1.0000000000000000e+30"/>
    </Bin>
    <Bin ibin="15" effS="1.4000000000000001e-01" effB="1.2817226815968752e-03">
      <Cuts cutMin_0="-1.0000000000000000e+30" cutMax_0="6.3043816757811311e-03" cutMin_1="7.5830121910026058e+00" cutMax_1="1.0000000000000000e+30"/>
    </Bin>
    <Bin ibin="16" effS="1.4999999999999999e-01" effB="1.4739810721948743e-03">
      <Cuts cutMin_0="-1.0000000000000000e+30" cutMax_0="7.4260694475748604e-03" cutMin_1="7.8620275856005559e+00" cutMax_1="1.0000000000000000e+30"/>
    </Bin>
    <Bin ibin="17" effS="1.6000000000000000e-01" effB="1.6662394627928734e-03">
      <Cuts cutMin_0="-1.0000000000000000e+30" cutMax_0="6.2475761283309244e-03" cutMin_1="3.7901531753106377e+00" cutMax_1="1.0000000000000000e+30"/>
    </Bin>
    <Bin ibin="18" effS="1.7000000000000001e-01" effB="2.1148424129933119e-03">
      <Cuts cutMin_0="-1.0000000000000000e+30" cutMax_0="1.0237323533130116e-02" cutMin_1="9.3155827822137560e+00" cutMax_1="1.0000000000000000e+30"/>
    </Bin>
    <Bin ibin="19" effS="1.7999999999999999e-01" effB="1.9225839059799910e-03">
      <Cuts cutMin_0="-1.0000000000000000e+30" cutMax_0="7.5353980399288480e-03" cutMin_1="5.4294069300711296e+00" cutMax_1="1.0000000000000000e+30"/>
    </Bin>
    <Bin ibin="20" effS="1.9000000000000000e-01" effB="1.9866700749844313e-03">
      <Cuts cutMin_0="-1.0000000000000000e+30" cutMax_0="7.1100560963369636e-03" cutMin_1="3.6830457982904559e+00" cutMax_1="1.0000000000000000e+30"/>
    </Bin>
    <Bin ibin="21" effS="2.0000000000000001e-01" effB="2.5634453631937504e-03">
      <Cuts cutMin_0="-1.0000000000000000e+30" cutMax_0="1.2716614769964732e-02" cutMin_1="9.2204880720729268e+00" cutMax_1="1.0000000000000000e+30"/>
    </Bin>
    <Bin ibin="22" effS="2.0999999999999999e-01" effB="3.2043065875768661e-03">
      <Cuts cutMin_0="-1.0000000000000000e+30" cutMax_0="1.4237379726882562e-02" cutMin_1="9.1381669138088668e+00" cutMax_1="1.0000000000000000e+30"/>
    </Bin>
    <Bin ibin="23" effS="2.2000000000000000e-01" effB="7.1135605685412884e-03">
      <Cuts cutMin_0="-1.0000000000000000e+30" cutMax_0="2.8774514555888836e-02" cutMin_1="1.0238509078378421e+01" cutMax_1="1.0000000000000000e+30"/>
    </Bin>
    <Bin ibin="24" effS="2.3000000000000001e-01" effB="2.5634453631937504e-03">
      <Cuts cutMin_0="-1.0000000000000000e+30" cutMax_0="1.0461905877517243e-02" cutMin_1="6.1883407591638147e+00" cutMax_1="1.0000000000000000e+30"/>
    </Bin>
    <Bin ibin="25" effS="2.3999999999999999e-01" effB="2.7557036373764277e-03">
      <Cuts cutMin_0="-1.0000000000000000e+30" cutMax_0="9.8283871566306087e-03" cutMin_1="5.3626567805413163e+00" cutMax_1="1.0000000000000000e+30"/>
    </Bin>
    <Bin ibin="26" effS="2.5000000000000000e-01" effB="5.7036657817661762e-03">
      <Cuts cutMin_0="-1.0000000000000000e+30" cutMax_0="2.3444879727705370e-02" cutMin_1="8.8635597845213763e+00" cutMax_1="1.0000000000000000e+30"/>
    </Bin>
    <Bin ibin="27" effS="2.6000000000000001e-01" effB="4.7423737123608589e-03">
      <Cuts cutMin_0="-1.0000000000000000e+30" cutMax_0="1.9296270728150065e-02" cutMin_1="8.1312585193429232e+00" cutMax_1="1.0000000000000000e+30"/>
    </Bin>
    <Bin ibin="28" effS="2.7000000000000002e-01" effB="3.0761342495679855e-03">
      <Cuts cutMin_0="-1.0000000000000000e+30" cutMax_0="1.2347073544843250e-02" cutMin_1="6.0091536467166708e+00" cutMax_1="1.0000000000000000e+30"/>
    </Bin>
    <Bin ibin="29" effS="2.8000000000000003e-01" effB="3.4606510307639837e-03">
      <Cuts cutMin_0="-1.0000000000000000e+30" cutMax_0="1.2673281587362164e-02" cutMin_1="5.6891459267982381e+00" cutMax_1="1.0000000000000000e+30"/>
    </Bin>
    <Bin ibin="30" effS="2.8999999999999998e-01" effB="3.6529095377773046e-03">
      <Cuts cutMin_0="-1.0000000000000000e+30" cutMax_0="1.1577028216823274e-02" cutMin_1="4.2986993160630425e+00" cutMax_1="1.0000000000000000e+30"/>
    </Bin>
    <Bin ibin="31" effS="2.9999999999999999e-01" effB="4.2937709949910641e-03">
      <Cuts cutMin_0="-1.0000000000000000e+30" cutMax_0="1.0913632066053912e-02" cutMin_1="2.8393607404505441e+00" cutMax_1="1.0000000000000000e+30"/>
    </Bin>
    <Bin ibin="32" effS="3.1000000000000000e-01" effB="4.5501152053475380e-03">
      <Cuts cutMin_0="-1.0000000000000000e+30" cutMax_0="1.7616209579163822e-02" cutMin_1="6.6098926790927646e+00" cutMax_1="1.0000000000000000e+30"/>
    </Bin>
    <Bin ibin="33" effS="3.2000000000000001e-01" effB="4.6142013743519783e-03">
      <Cuts cutMin_0="-1.0000000000000000e+30" cutMax_0="1.1749101736940798e-02" cutMin_1="2.8542706329769807e+00" cutMax_1="1.0000000000000000e+30"/>
    </Bin>
    <Bin ibin="34" effS="3.3000000000000002e-01" effB="5.8318381197750568e-03">
      <Cuts cutMin_0="-1.0000000000000000e+30" cutMax_0="2.0756785141734735e-02" cutMin_1="6.5746652014157601e+00" cutMax_1="1.0000000000000000e+30"/>
    </Bin>
    <Bin ibin="35" effS="3.4000000000000002e-01" effB="4.8705460503697395e-03">
      <Cuts cutMin_0="-1.0000000000000000e+30" cutMax_0="1.4225587680902537e-02" cutMin_1="4.1880715186931718e+00" cutMax_1="1.0000000000000000e+30"/>
    </Bin>
    <Bin ibin="36" effS="3.5000000000000003e-01" effB="5.6395796127617359e-03">
      <Cuts cutMin_0="-1.0000000000000000e+30" cutMax_0="1.8213868526607030e-02" cutMin_1="5.4299101370368676e+00" cutMax_1="1.0000000000000000e+30"/>
    </Bin>
    <Bin ibin="37" effS="3.5999999999999999e-01" effB="5.6395796127617359e-03">
      <Cuts cutMin_0="-1.0000000000000000e+30" cutMax_0="1.8200952055325244e-02" cutMin_1="5.3700497720991782e+00" cutMax_1="1.0000000000000000e+30"/>
    </Bin>
    <Bin ibin="38" effS="3.7000000000000000e-01" effB="5.6395796127617359e-03">
      <Cuts cutMin_0="-1.0000000000000000e+30" cutMax_0="1.5629835324502780e-02" cutMin_1="3.9777719099046198e+00" cutMax_1="1.0000000000000000e+30"/>
    </Bin>
    <Bin ibin="39" effS="3.8000000000000000e-01" effB="6.1522684991359711e-03">
      <Cuts cutMin_0="-1.0000000000000000e+30" cutMax_0="1.9139719719838084e-02" cutMin_1="4.9042490210975913e+00" cutMax_1="1.0000000000000000e+30"/>
    </Bin>
    <Bin ibin="40" effS="3.9000000000000001e-01" effB="6.4086131751537323e-03">
      <Cuts cutMin_0="-1.0000000000000000e+30" cutMax_0="1.9198799587663171e-02" cutMin_1="4.8236386129834985e+00" cutMax_1="1.0000000000000000e+30"/>
    </Bin>
    <Bin ibin="41" effS="4.0000000000000002e-01" effB="6.6008716821670532e-03">
      <Cuts cutMin_0="-1.0000000000000000e+30" cutMax_0="1.6768332310326050e-02" cutMin_1="3.4911683616523987e+00" cutMax_1="1.0000000000000000e+30"/>
    </Bin>
    <Bin ibin="42" effS="4.1000000000000003e-01" effB="7.1135605685412884e-03">
      <Cuts cutMin_0="-1.0000000000000000e+30" cutMax_0="1.9446287971518816e-02" cutMin_1="4.2432295377112483e+00" cutMax_1="1.0000000000000000e+30"/>
    </Bin>
    <Bin ibin="43" effS="4.1999999999999998e-01" effB="7.3058190755546093e-03">
      <Cuts cutMin_0="-1.0000000000000000e+30" cutMax_0="1.8703911590579152e-02" cutMin_1="3.7911575251707887e+00" cutMax_1="1.0000000000000000e+30"/>
    </Bin>
    <Bin ibin="44" effS="4.2999999999999999e-01" effB="7.8185079619288445e-03">
      <Cuts cutMin_0="-1.0000000000000000e+30" cutMax_0="1.7809824021877141e-02" cutMin_1="3.0601055167451383e+00" cutMax_1="1.0000000000000000e+30"/>
    </Bin>
    <Bin ibin="45" effS="4.4000000000000000e-01" effB="7.9466802999377251e-03">
      <Cuts cutMin_0="-1.0000000000000000e+30" cutMax_0="1.9664525755812422e-02" cutMin_1="3.6094982347455731e+00" cutMax_1="1.0000000000000000e+30"/>
    </Bin>
    <Bin ibin="46" effS="4.5000000000000001e-01" effB="9.0361442416906357e-03">
      <Cuts cutMin_0="-1.0000000000000000e+30" cutMax_0="2.1020238711373273e-02" cutMin_1="3.7171811076964754e+00" cutMax_1="1.0000000000000000e+30"/>
    </Bin>
    <Bin ibin="47" effS="4.6000000000000002e-01" effB="9.2284027487039566e-03">
      <Cuts cutMin_0="-1.0000000000000000e+30" cutMax_0="2.0542850289306455e-02" cutMin_1="3.3520877555934177e+00" cutMax_1="1.0000000000000000e+30"/>
    </Bin>
    <Bin ibin="48" effS="4.7000000000000003e-01" effB="1.0125609114766121e-02">
      <Cuts cutMin_0="-1.0000000000000000e+30" cutMax_0="2.2220144109168366e-02" cutMin_1="3.4899176544654082e+00" cutMax_1="1.0000000000000000e+30"/>
    </Bin>
    <Bin ibin="49" effS="4.7999999999999998e-01" effB="1.0381953790783882e-02">
      <Cuts cutMin_0="-1.0000000000000000e+30" cutMax_0="2.2688157421139037e-02" cutMin_1="3.4831386806615585e+00" cutMax_1="1.0000000000000000e+30"/>
    </Bin>
    <Bin ibin="50" effS="4.8999999999999999e-01" effB="1.1086900718510151e-02">
      <Cuts cutMin_0="-1.0000000000000000e+30" cutMax_0="2.2219072917745487e-02" cutMin_1="3.1616889845139435e+00" cutMax_1="1.0000000000000000e+30"/>
    </Bin>
    <Bin ibin="51" effS="5.0000000000000000e-01" effB="1.1791848577558994e-02">
      <Cuts cutMin_0="-1.0000000000000000e+30" cutMax_0="2.4172788066252903e-02" cutMin_1="3.3554785895784978e+00" cutMax_1="1.0000000000000000e+30"/>
    </Bin>
    <Bin ibin="52" effS="5.1000000000000001e-01" effB="1.2560881674289703e-02">
      <Cuts cutMin_0="-1.0000000000000000e+30" cutMax_0="2.4819263149422066e-02" cutMin_1="3.2193394405451663e+00" cutMax_1="1.0000000000000000e+30"/>
    </Bin>
    <Bin ibin="53" effS="5.2000000000000002e-01" effB="1.2881312519311905e-02">
      <Cuts cutMin_0="-1.0000000000000000e+30" cutMax_0="2.5195501414832774e-02" cutMin_1="3.1754624059119672e+00" cutMax_1="1.0000000000000000e+30"/>
    </Bin>
    <Bin ibin="54" effS="5.3000000000000003e-01" effB="1.3329915702342987e-02">
      <Cuts cutMin_0="-1.0000000000000000e+30" cutMax_0="2.5404269355960261e-02" cutMin_1="3.0263751553958307e+00" cutMax_1="1.0000000000000000e+30"/>
    </Bin>
    <Bin ibin="55" effS="5.4000000000000004e-01" effB="1.4867982827126980e-02">
      <Cuts cutMin_0="-1.0000000000000000e+30" cutMax_0="2.9926654178818388e-02" cutMin_1="3.4920188978334199e+00" cutMax_1="1.0000000000000000e+30"/>
    </Bin>
    <Bin ibin="56" effS="5.5000000000000004e-01" effB="1.5444757416844368e-02">
      <Cuts cutMin_0="-1.0000000000000000e+30" cutMax_0="2.7495556187273822e-02" cutMin_1="2.9512295704324130e+00" cutMax_1="1.0000000000000000e+30"/>
    </Bin>
    <Bin ibin="57" effS="5.6000000000000005e-01" effB="1.6341963782906532e-02">
      <Cuts cutMin_0="-1.0000000000000000e+30" cutMax_0="2.9927256060025997e-02" cutMin_1="3.0854646780221624e+00" cutMax_1="1.0000000000000000e+30"/>
    </Bin>
    <Bin ibin="58" effS="5.7000000000000006e-01" effB="1.6470136120915413e-02">
      <Cuts cutMin_0="-1.0000000000000000e+30" cutMax_0="2.9938731346801660e-02" cutMin_1="3.0664156799027160e+00" cutMax_1="1.0000000000000000e+30"/>
    </Bin>
    <Bin ibin="59" effS="5.7999999999999996e-01" effB="1.7687771469354630e-02">
      <Cuts cutMin_0="-1.0000000000000000e+30" cutMax_0="3.0157131046933711e-02" cutMin_1="2.9063971657875447e+00" cutMax_1="1.0000000000000000e+30"/>
    </Bin>
    <Bin ibin="60" effS="5.8999999999999997e-01" effB="1.8392719328403473e-02">
      <Cuts cutMin_0="-1.0000000000000000e+30" cutMax_0="3.0821591980802428e-02" cutMin_1="2.8837707303870821e+00" cutMax_1="1.0000000000000000e+30"/>
    </Bin>
    <Bin ibin="61" effS="5.9999999999999998e-01" effB="2.1725198253989220e-02">
      <Cuts cutMin_0="-1.0000000000000000e+30" cutMax_0="3.5196480844828973e-02" cutMin_1="3.0314260410329288e+00" cutMax_1="1.0000000000000000e+30"/>
    </Bin>
    <Bin ibin="62" effS="6.0999999999999999e-01" effB="2.4480901658535004e-02">
      <Cuts cutMin_0="-1.0000000000000000e+30" cutMax_0="3.9134136780193118e-02" cutMin_1="3.1624350322840598e+00" cutMax_1="1.0000000000000000e+30"/>
    </Bin>
    <Bin ibin="63" effS="6.2000000000000000e-01" effB="2.4993591010570526e-02">
      <Cuts cutMin_0="-1.0000000000000000e+30" cutMax_0="3.7191465645076270e-02" cutMin_1="2.8804529854268091e+00" cutMax_1="1.0000000000000000e+30"/>
    </Bin>
    <Bin ibin="64" effS="6.3000000000000000e-01" effB="2.7813380584120750e-02">
      <Cuts cutMin_0="-1.0000000000000000e+30" cutMax_0="4.1752746265558957e-02" cutMin_1="3.0137862238462354e+00" cutMax_1="1.0000000000000000e+30"/>
    </Bin>
    <Bin ibin="65" effS="6.4000000000000001e-01" effB="2.9735965654253960e-02">
      <Cuts cutMin_0="-1.0000000000000000e+30" cutMax_0="3.9474546753714188e-02" cutMin_1="2.7859280857807374e+00" cutMax_1="1.0000000000000000e+30"/>
    </Bin>
    <Bin ibin="66" effS="6.5000000000000002e-01" effB="3.2748013734817505e-02">
      <Cuts cutMin_0="-1.0000000000000000e+30" cutMax_0="4.3140400276085018e-02" cutMin_1="2.8127006405139374e+00" cutMax_1="1.0000000000000000e+30"/>
    </Bin>
    <Bin ibin="67" effS="6.6000000000000003e-01" effB="3.5952318459749222e-02">
      <Cuts cutMin_0="-1.0000000000000000e+30" cutMax_0="4.2219639190905892e-02" cutMin_1="2.6069261519075910e+00" cutMax_1="1.0000000000000000e+30"/>
    </Bin>
    <Bin ibin="68" effS="6.7000000000000004e-01" effB="3.9028454571962357e-02">
      <Cuts cutMin_0="-1.0000000000000000e+30" cutMax_0="4.4743053041122430e-02" cutMin_1="2.6015285080339385e+00" cutMax_1="1.0000000000000000e+30"/>
    </Bin>
    <Bin ibin="69" effS="6.8000000000000005e-01" effB="4.1527815163135529e-02">
      <Cuts cutMin_0="-1.0000000000000000e+30" cutMax_0="4.4427840126274348e-02" cutMin_1="2.4859867645668983e+00" cutMax_1="1.0000000000000000e+30"/>
    </Bin>
    <Bin ibin="70" effS="6.9000000000000006e-01" effB="4.5949757099151611e-02">
      <Cuts cutMin_0="-1.0000000000000000e+30" cutMax_0="4.3961730854389591e-02" cutMin_1="2.3037275795689753e+00" cutMax_1="1.0000000000000000e+30"/>
    </Bin>
    <Bin ibin="71" effS="7.0000000000000007e-01" effB="4.8513200134038925e-02">
      <Cuts cutMin_0="-1.0000000000000000e+30" cutMax_0="5.0644505469993467e-02" cutMin_1="2.4857709182638308e+00" cutMax_1="1.0000000000000000e+30"/>
    </Bin>
    <Bin ibin="72" effS="7.0999999999999996e-01" effB="5.2486542612314224e-02">
      <Cuts cutMin_0="-1.0000000000000000e+30" cutMax_0="4.7054654102765693e-02" cutMin_1="2.2394849161892472e+00" cutMax_1="1.0000000000000000e+30"/>
    </Bin>
    <Bin ibin="73" effS="7.1999999999999997e-01" effB="5.8190207928419113e-02">
      <Cuts cutMin_0="-1.0000000000000000e+30" cutMax_0="5.3252427706766269e-02" cutMin_1="2.2632140888504302e+00" cutMax_1="1.0000000000000000e+30"/>
    </Bin>
    <Bin ibin="74" effS="7.2999999999999998e-01" effB="6.1843115836381912e-02">
      <Cuts cutMin_0="-1.0000000000000000e+30" cutMax_0="5.4498604334341748e-02" cutMin_1="2.2336662028264711e+00" cutMax_1="1.0000000000000000e+30"/>
    </Bin>
    <Bin ibin="75" effS="7.3999999999999999e-01" effB="6.7482694983482361e-02">
      <Cuts cutMin_0="-1.0000000000000000e+30" cutMax_0="6.3377746330428503e-02" cutMin_1="2.3313219996583423e+00" cutMax_1="1.0000000000000000e+30"/>
    </Bin>
    <Bin ibin="76" effS="7.5000000000000000e-01" effB="7.3699049651622772e-02">
      <Cuts cutMin_0="-1.0000000000000000e+30" cutMax_0="5.9544039215390067e-02" cutMin_1="2.1340775990406540e+00" cutMax_1="1.0000000000000000e+30"/>
    </Bin>
    <Bin ibin="77" effS="7.6000000000000001e-01" effB="7.9530887305736542e-02">
      <Cuts cutMin_0="-1.0000000000000000e+30" cutMax_0="6.3282991563109792e-02" cutMin_1="2.1128627796504240e+00" cutMax_1="1.0000000000000000e+30"/>
    </Bin>
    <Bin ibin="78" effS="7.7000000000000002e-01" effB="8.6644448339939117e-02">
      <Cuts cutMin_0="-1.0000000000000000e+30" cutMax_0="6.8802999337291698e-02" cutMin_1="2.0899293954406142e+00" cutMax_1="1.0000000000000000e+30"/>
    </Bin>
    <Bin ibin="79" effS="7.8000000000000003e-01" effB="9.5296077430248260e-02">
      <Cuts cutMin_0="-1.0000000000000000e+30" cutMax_0="7.2041858827899458e-02" cutMin_1="2.0294676426784322e+00" cutMax_1="1.0000000000000000e+30"/>
    </Bin>
    <Bin ibin="80" effS="7.9000000000000004e-01" effB="1.0381953418254852e-01">
      <Cuts cutMin_0="-1.0000000000000000e+30" cutMax_0="7.1236117901374296e-02" cutMin_1="1.9290607954381298e+00" cutMax_1="1.0000000000000000e+30"/>
    </Bin>
    <Bin ibin="81" effS="8.0000000000000004e-01" effB="1.1368879675865173e-01">
      <Cuts cutMin_0="-1.0000000000000000e+30" cutMax_0="7.8817977937485184e-02" cutMin_1="1.9167788616662227e+00" cutMax_1="1.0000000000000000e+30"/>
    </Bin>
    <Bin ibin="82" effS="8.1000000000000005e-01" effB="1.2509612739086151e-01">
      <Cuts cutMin_0="-1.0000000000000000e+30" cutMax_0="8.1271962478098023e-02" cutMin_1="1.8335358786560474e+00" cutMax_1="1.0000000000000000e+30"/>
    </Bin>
    <Bin ibin="83" effS="8.2000000000000006e-01" effB="1.3874647021293640e-01">
      <Cuts cutMin_0="-1.0000000000000000e+30" cutMax_0="8.0434991556994156e-02" cutMin_1="1.7269869878017161e+00" cutMax_1="1.0000000000000000e+30"/>
    </Bin>
    <Bin ibin="84" effS="8.3000000000000007e-01" effB="1.5534478425979614e-01">
      <Cuts cutMin_0="-1.0000000000000000e+30" cutMax_0="8.4245453060974515e-02" cutMin_1="1.6555431205932987e+00" cutMax_1="1.0000000000000000e+30"/>
    </Bin>
    <Bin ibin="85" effS="8.3999999999999997e-01" effB="1.7296847701072693e-01">
      <Cuts cutMin_0="-1.0000000000000000e+30" cutMax_0="8.7006148513063278e-02" cutMin_1="1.5882687873868389e+00" cutMax_1="1.0000000000000000e+30"/>
    </Bin>
    <Bin ibin="86" effS="8.4999999999999998e-01" effB="1.9078440964221954e-01">
      <Cuts cutMin_0="-1.0000000000000000e+30" cutMax_0="8.5910883360974438e-02" cutMin_1="1.4955287112531490e+00" cutMax_1="1.0000000000000000e+30"/>
    </Bin>
    <Bin ibin="87" effS="8.5999999999999999e-01" effB="2.1129198372364044e-01">
      <Cuts cutMin_0="-1.0000000000000000e+30" cutMax_0="8.5943705709095194e-02" cutMin_1="1.4052634086652953e+00" cutMax_1="1.0000000000000000e+30"/>
    </Bin>
    <Bin ibin="88" effS="8.7000000000000000e-01" effB="2.3314534127712250e-01">
      <Cuts cutMin_0="-1.0000000000000000e+30" cutMax_0="9.3685221756678413e-02" cutMin_1="1.3646891317553611e+00" cutMax_1="1.0000000000000000e+30"/>
    </Bin>
    <Bin ibin="89" effS="8.8000000000000000e-01" effB="2.6557293534278870e-01">
      <Cuts cutMin_0="-1.0000000000000000e+30" cutMax_0="1.0289438291471573e-01" cutMin_1="1.3018300706914356e+00" cutMax_1="1.0000000000000000e+30"/>
    </Bin>
    <Bin ibin="90" effS="8.9000000000000001e-01" effB="2.9588568210601807e-01">
      <Cuts cutMin_0="-1.0000000000000000e+30" cutMax_0="9.2856159347807846e-02" cutMin_1="1.1422534828841207e+00" cutMax_1="1.0000000000000000e+30"/>
    </Bin>
    <Bin ibin="91" effS="9.0000000000000002e-01" effB="3.3247885107994080e-01">
      <Cuts cutMin_0="-1.0000000000000000e+30" cutMax_0="1.0169882081773639e-01" cutMin_1="1.0937988780577617e+00" cutMax_1="1.0000000000000000e+30"/>
    </Bin>
    <Bin ibin="92" effS="9.1000000000000003e-01" effB="3.6875161528587341e-01">
      <Cuts cutMin_0="-1.0000000000000000e+30" cutMax_0="1.3304677624963410e-01" cutMin_1="1.1235491275391798e+00" cutMax_1="1.0000000000000000e+30"/>
    </Bin>
    <Bin ibin="93" effS="9.2000000000000004e-01" effB="4.1380414366722107e-01">
      <Cuts cutMin_0="-1.0000000000000000e+30" cutMax_0="1.4203983006312165e-01" cutMin_1="1.0429483963240238e+00" cutMax_1="1.0000000000000000e+30"/>
    </Bin>
    <Bin ibin="94" effS="9.3000000000000005e-01" effB="4.6911048889160156e-01">
      <Cuts cutMin_0="-1.0000000000000000e+30" cutMax_0="1.8477510467605263e-01" cutMin_1="1.0087512462909594e+00" cutMax_1="1.0000000000000000e+30"/>
    </Bin>
    <Bin ibin="95" effS="9.4000000000000006e-01" effB="5.2223789691925049e-01">
      <Cuts cutMin_0="-1.0000000000000000e+30" cutMax_0="1.4175034930741023e-01" cutMin_1="8.3930641136751083e-01" cutMax_1="1.0000000000000000e+30"/>
    </Bin>
    <Bin ibin="96" effS="9.5000000000000007e-01" effB="5.8036398887634277e-01">
      <Cuts cutMin_0="-1.0000000000000000e+30" cutMax_0="1.6425642384948436e-01" cutMin_1="7.9509537375094763e-01" cutMax_1="1.0000000000000000e+30"/>
    </Bin>
    <Bin ibin="97" effS="9.5999999999999996e-01" effB="6.5342217683792114e-01">
      <Cuts cutMin_0="-1.0000000000000000e+30" cutMax_0="1.4204595131863776e-01" cutMin_1="6.0500040671794164e-01" cutMax_1="1.0000000000000000e+30"/>
    </Bin>
    <Bin ibin="98" effS="9.6999999999999997e-01" effB="7.1923863887786865e-01">
      <Cuts cutMin_0="-1.0000000000000000e+30" cutMax_0="1.4339443256597456e-01" cutMin_1="4.8192806273869626e-01" cutMax_1="1.0000000000000000e+30"/>
    </Bin>
    <Bin ibin="99" effS="9.7999999999999998e-01" effB="7.9646241664886475e-01">
      <Cuts cutMin_0="-1.0000000000000000e+30" cutMax_0="1.7973441904697959e-01" cutMin_1="4.9255753006723424e-01" cutMax_1="1.0000000000000000e+30"/>
    </Bin>
    <Bin ibin="100" effS="9.8999999999999999e-01" effB="8.8547807931900024e-01">
      <Cuts cutMin_0="-1.0000000000000000e+30" cutMax_0="1.7867943323464999e-01" cutMin_1="3.1649690730050217e-01" cutMax_1="1.0000000000000000e+30"/>
    </Bin>
  </Weights>
</MethodSetup>
